.gitignore
CHANGES.txt
README.rst
demo.py
setup.py
tox.ini
miniadt/__init__.py
miniadt/adttype.py
miniadt/langhelpers.py
miniadt.egg-info/PKG-INFO
miniadt.egg-info/SOURCES.txt
miniadt.egg-info/dependency_links.txt
miniadt.egg-info/entry_points.txt
miniadt.egg-info/not-zip-safe
miniadt.egg-info/pbr.json
miniadt.egg-info/requires.txt
miniadt.egg-info/top_level.txt
miniadt/tests/__init__.py
miniadt/tests/test_equality.py
miniadt/tests/test_hierarchy.py
miniadt/tests/test_it.py