Metadata-Version: 1.1
Name: miniadt
Version: 0.4.0
Summary: tiny abstract data type on python
Home-page: UNKNOWN
Author: UNKNOWN
Author-email: UNKNOWN
License: UNKNOWN
Platform: UNKNOWN
Classifier: Programming Language :: Python
Classifier: Programming Language :: Python :: Implementation :: CPython
